uqtopus/__init__.py
uqtopus/core/__init__.py
uqtopus/core/sampling.py
uqtopus/core/uq_runner.py
uqtopus/utils/__init__.py
uqtopus/utils/openfoam_tools.py
uqtopus-0.1.1.dist-info/METADATA
uqtopus-0.1.1.dist-info/WHEEL
uqtopus-0.1.1.dist-info/licenses/LICENSE
uqtopus-0.1.1.dist-info/RECORD
