Metadata-Version: 2.4
Name: uqtopus
Version: 0.1.1
Summary: Uncertainty Quantification Toolbox for OpenFOAM and Python Unified Simulation workflows
Project-URL: Homepage, https://github.com/GBdeMiranda/uqtopus
Project-URL: Repository, https://github.com/GBdeMiranda/uqtopus
Author-email: Gabriel Brandao de Miranda <gabrielbrandaodemiranda@gmail.com>
License: MIT License
License-File: LICENSE
Requires-Dist: fluidfoam<0.3.0,>=0.2.9
Requires-Dist: jinja2<4.0.0,>=3.1.6
Requires-Dist: numpy<2.0.0,>=1.21.0
Requires-Dist: pydoe3<2.0.0,>=1.2.0
Requires-Dist: pyyaml<7.0.0,>=6.0.2
Requires-Dist: tqdm<5.0.0,>=4.66.5
Requires-Dist: xarray<2026.0.0,>=2024.6.0
Provides-Extra: dev
Requires-Dist: ipython; extra == 'dev'
Requires-Dist: uv>=0.1.0; extra == 'dev'
Provides-Extra: test
Requires-Dist: ipython; extra == 'test'
Requires-Dist: matplotlib>=3.5.0; extra == 'test'
Requires-Dist: pytest; extra == 'test'
Requires-Dist: python-dotenv>=1.1.1; extra == 'test'
Requires-Dist: setuptools>=75.1.0; extra == 'test'
Requires-Dist: uqpylab>=1.0.2; extra == 'test'
